traffic_generation_utils/__init__.py
traffic_generation_utils/monitoring_engines/__init__.py
traffic_generation_utils/monitoring_engines/package_capture.py
traffic_generation_utils-0.0.1.dist-info/LICENSE
traffic_generation_utils-0.0.1.dist-info/WHEEL
traffic_generation_utils-0.0.1.dist-info/METADATA
traffic_generation_utils-0.0.1.dist-info/RECORD
